traceforest/__init__.py
traceforest/constants.py
traceforest/exporters/__init__.py
traceforest/exporters/exporter.py
traceforest/exporters/shell_exporter.py
traceforest/exporters/web_exporter.py
traceforest/nodes/__init__.py
traceforest/nodes/adapters/__init__.py
traceforest/nodes/adapters/json_adapter.py
traceforest/nodes/node.py
traceforest/profiler.py
traceforest-0.1.7.dist-info/METADATA
traceforest-0.1.7.dist-info/WHEEL
traceforest-0.1.7.dist-info/RECORD
