Metadata-Version: 2.3
Name: traceforest
Version: 0.1.7
Summary: High-performance Python profiler that generates interactive call tree visualizations to identify execution bottlenecks.
Author: sandro.meireles
Author-email: sandro.meirelesdev@gmail.com
Requires-Python: >=3.9
Classifier: Programming Language :: Python :: 3
Classifier: Programming Language :: Python :: 3.9
Classifier: Programming Language :: Python :: 3.10
Classifier: Programming Language :: Python :: 3.11
Classifier: Programming Language :: Python :: 3.12
Classifier: Programming Language :: Python :: 3.13
Provides-Extra: dev
Requires-Dist: flake8 ; extra == "dev"
Requires-Dist: requests (>=2.32.5,<3.0.0)
